{"buildname":"2021-10-18_23h26m26s","ended":"1634590346","jailname":"Cygate_v2_5_0_amd64","mastername":"Cygate_v2_5_0_amd64-Cygate_devel","ports":{"built":[{"origin":"sysutils/Cygate-repo","pkgname":"Cygate-repo-2.6.0.a.20211018.2326","elapsed":"1"},{"origin":"net-mgmt/bandwidthd","pkgname":"bandwidthd-2.0.1_12","elapsed":"73"},{"origin":"ftp/php74-ftp","pkgname":"php74-ftp-7.4.24","elapsed":"10"},{"origin":"sysutils/Cygate-Status_Monitoring","flavor":"php74","pkgname":"Cygate-Status_Monitoring-1.7.11_4","elapsed":"10"},{"origin":"devel/php74-readline","pkgname":"php74-readline-7.4.24","elapsed":"12"},{"origin":"sysutils/syslog-ng","pkgname":"syslog-ng-3.34.1","elapsed":"107"},{"origin":"devel/php74-sysvmsg","pkgname":"php74-sysvmsg-7.4.24","elapsed":"10"},{"origin":"net/php74-sockets","pkgname":"php74-sockets-7.4.24","elapsed":"9"},{"origin":"sysutils/filterlog","pkgname":"filterlog-0.1_6","elapsed":"3"},{"origin":"net/filterdns","pkgname":"filterdns-2.0_5","elapsed":"5"},{"origin":"comms/py-pyserial","flavor":"py38","pkgname":"py38-pyserial-3.5_1","elapsed":"8"},{"origin":"sysutils/apcupsd","pkgname":"apcupsd-3.14.14_4","elapsed":"9"},{"origin":"net/vnstat","pkgname":"vnstat-2.8","elapsed":"8"},{"origin":"www/Cygate-pkg-squid","pkgname":"Cygate-pkg-squid-0.4.45_5","elapsed":"15"},{"origin":"databases/php74-pdo_sqlite","pkgname":"php74-pdo_sqlite-7.4.24","elapsed":"13"},{"origin":"net/mobile-broadband-provider-info","pkgname":"mobile-broadband-provider-info-20210805","elapsed":"10"},{"origin":"devel/php74-gettext","pkgname":"php74-gettext-7.4.24","elapsed":"12"},{"origin":"net-mgmt/zabbix5-agent","pkgname":"zabbix5-agent-5.0.16","elapsed":"18"},{"origin":"devel/php-Cygate-module","flavor":"php74","pkgname":"php74-Cygate-module-0.74","elapsed":"13"},{"origin":"sysutils/pftop","pkgname":"pftop-0.7_9","elapsed":"8"},{"origin":"archivers/php74-bz2","pkgname":"php74-bz2-7.4.24","elapsed":"10"},{"origin":"sysutils/lsof","pkgname":"lsof-4.94.0,8","elapsed":"8"},{"origin":"net/radvd","pkgname":"radvd-2.19_2","elapsed":"7"},{"origin":"net/avahi-app","pkgname":"avahi-app-0.8","elapsed":"21"},{"origin":"security/openvpn-client-export","pkgname":"openvpn-client-export-2.5.2","elapsed":"14"},{"origin":"sysutils/node_exporter","pkgname":"node_exporter-1.2.2","elapsed":"31"},{"origin":"audio/beep","pkgname":"beep-1.0_1","elapsed":"4"},{"origin":"dns/dnsmasq","pkgname":"dnsmasq-2.86,1","elapsed":"10"},{"origin":"devel/php74-intl","pkgname":"php74-intl-7.4.24","elapsed":"17"},{"origin":"security/phpseclib","flavor":"php74","pkgname":"php74-phpseclib-2.0.17","elapsed":"5"},{"origin":"net/igmpproxy","pkgname":"igmpproxy-0.3,1","elapsed":"11"},{"origin":"net-mgmt/zabbix4-agent","pkgname":"zabbix4-agent-4.0.30","elapsed":"18"},{"origin":"www/squidguard","pkgname":"squidGuard-1.4_15","elapsed":"11"},{"origin":"security/expiretable","pkgname":"expiretable-0.6_2","elapsed":"4"},{"origin":"security/xinetd","pkgname":"xinetd-2.3.15_2","elapsed":"8"},{"origin":"net/socat","pkgname":"socat-1.7.4.1_1","elapsed":"12"},{"origin":"sysutils/wrapalixresetbutton","pkgname":"wrapalixresetbutton-0.0.8","elapsed":"3"},{"origin":"net-mgmt/bsnmp-regex","pkgname":"bsnmp-regex-0.6_2","elapsed":"7"},{"origin":"net-mgmt/iprange","pkgname":"iprange-1.0.4","elapsed":"5"},{"origin":"net-mgmt/zabbix3-proxy","pkgname":"zabbix3-proxy-3.0.32","elapsed":"31"},{"origin":"devel/libccid","pkgname":"ccid-1.4.36","elapsed":"10"},{"origin":"net-mgmt/choparp","pkgname":"choparp-20150613","elapsed":"5"},{"origin":"devel/php74-shmop","pkgname":"php74-shmop-7.4.24","elapsed":"10"},{"origin":"sysutils/qstats","pkgname":"qstats-0.2","elapsed":"4"},{"origin":"sysutils/php74-posix","pkgname":"php74-posix-7.4.24","elapsed":"11"},{"origin":"net/ladvd","pkgname":"ladvd-1.1.2_1","elapsed":"16"},{"origin":"net-mgmt/zabbix5-proxy","pkgname":"zabbix5-proxy-5.0.16","elapsed":"58"},{"origin":"sysutils/cpustats","pkgname":"cpustats-0.1_1","elapsed":"4"},{"origin":"security/Cygate-pkg-tinc","pkgname":"Cygate-pkg-tinc-1.0.35_3","elapsed":"4"},{"origin":"sysutils/Cygate-pkg-nut","pkgname":"Cygate-pkg-nut-2.7.4_8","elapsed":"15"},{"origin":"net/mosh","pkgname":"mosh-1.3.2_17","elapsed":"82"},{"origin":"dns/dnstop","pkgname":"dnstop-20140915","elapsed":"24"},{"origin":"net/trafshow3","pkgname":"trafshow3-3.1_8,1","elapsed":"12"},{"origin":"net-mgmt/Cygate-pkg-zabbix-agent5","pkgname":"Cygate-pkg-zabbix-agent5-1.0.4_11","elapsed":"8"},{"origin":"security/Cygate-pkg-snort","pkgname":"Cygate-pkg-snort-4.1.4_3","elapsed":"12"},{"origin":"net-mgmt/Cygate-pkg-zabbix-proxy54","pkgname":"Cygate-pkg-zabbix-proxy54-1.0.4_11","elapsed":"18"},{"origin":"net/Cygate-pkg-haproxy-devel","pkgname":"Cygate-pkg-haproxy-devel-0.62_4","elapsed":"9"},{"origin":"sysutils/Cygate-pkg-Backup","pkgname":"Cygate-pkg-Backup-0.5_5","elapsed":"7"},{"origin":"net/Cygate-pkg-ntopng","pkgname":"Cygate-pkg-ntopng-0.8.13_10","elapsed":"31"},{"origin":"security/Cygate-pkg-nmap","pkgname":"Cygate-pkg-nmap-1.4.4_2","elapsed":"7"},{"origin":"net/Cygate-pkg-Status_Traffic_Totals","pkgname":"Cygate-pkg-Status_Traffic_Totals-2.3.2_2","elapsed":"9"},{"origin":"security/zeek","pkgname":"zeek-4.0.4","elapsed":"316"},{"origin":"net-mgmt/Cygate-pkg-zabbix-proxy","pkgname":"Cygate-pkg-zabbix-proxy-1.0.4_11","elapsed":"11"},{"origin":"databases/php74-pgsql","pkgname":"php74-pgsql-7.4.24","elapsed":"51"},{"origin":"net-mgmt/Cygate-pkg-zabbix-agent54","pkgname":"Cygate-pkg-zabbix-agent54-1.0.4_11","elapsed":"6"},{"origin":"security/Cygate-pkg-sudo","pkgname":"Cygate-pkg-sudo-0.3_6","elapsed":"7"},{"origin":"net/Cygate-pkg-freeradius3","pkgname":"Cygate-pkg-freeradius3-0.15.7_32","elapsed":"21"},{"origin":"sysutils/Cygate-pkg-Notes","pkgname":"Cygate-pkg-Notes-0.2.9_3","elapsed":"5"},{"origin":"sysutils/htop","pkgname":"htop-3.0.5","elapsed":"14"},{"origin":"sysutils/Cygate-pkg-Cron","pkgname":"Cygate-pkg-Cron-0.3.7_5","elapsed":"3"},{"origin":"net/Cygate-pkg-pimd","pkgname":"Cygate-pkg-pimd-0.0.3_4","elapsed":"3"},{"origin":"devel/gdb","flavor":"py38","pkgname":"gdb-11.1","elapsed":"193"},{"origin":"net/Cygate-pkg-LADVD","pkgname":"Cygate-pkg-LADVD-1.2.2_2","elapsed":"4"},{"origin":"net/Cygate-pkg-Avahi","pkgname":"Cygate-pkg-Avahi-2.2","elapsed":"8"},{"origin":"security/Cygate-pkg-acme","flavor":"php74","pkgname":"Cygate-pkg-acme-0.6.10","elapsed":"8"},{"origin":"sysutils/screen","pkgname":"screen-4.8.0_3","elapsed":"13"},{"origin":"databases/php74-mysqli","pkgname":"php74-mysqli-7.4.24","elapsed":"11"},{"origin":"editors/nano","pkgname":"nano-5.8","elapsed":"17"},{"origin":"sysutils/Cygate-pkg-LCDproc","pkgname":"Cygate-pkg-LCDproc-0.10.8_9","elapsed":"3"},{"origin":"sysutils/vm-bhyve","pkgname":"vm-bhyve-1.4.2","elapsed":"4"},{"origin":"net/trafshow","pkgname":"trafshow-5.2.3_3,1","elapsed":"5"},{"origin":"sysutils/Cygate-pkg-syslog-ng","pkgname":"Cygate-pkg-syslog-ng-1.15_11","elapsed":"14"},{"origin":"net-mgmt/Cygate-pkg-zabbix-proxy5","pkgname":"Cygate-pkg-zabbix-proxy5-1.0.4_11","elapsed":"13"},{"origin":"net/Cygate-pkg-frr","pkgname":"Cygate-pkg-frr-1.1.0_15","elapsed":"14"},{"origin":"net/hping","pkgname":"hping-2.0.0r3_2,1","elapsed":"12"},{"origin":"sysutils/tmux","pkgname":"tmux-3.2a","elapsed":"11"},{"origin":"sysutils/xe-guest-utilities","pkgname":"xe-guest-utilities-6.2.0_3","elapsed":"6"},{"origin":"net/Cygate-pkg-siproxd","pkgname":"Cygate-pkg-siproxd-1.1.4_1","elapsed":"7"},{"origin":"sysutils/Cygate-pkg-Netgate_Firmware_Upgrade","pkgname":"Cygate-pkg-Netgate_Firmware_Upgrade-0.40","elapsed":"22"},{"origin":"sysutils/Cygate-pkg-node_exporter","pkgname":"Cygate-pkg-node_exporter-0.18.1_3","elapsed":"6"},{"origin":"databases/php74-pdo_mysql","pkgname":"php74-pdo_mysql-7.4.24","elapsed":"11"},{"origin":"security/Cygate-pkg-openvpn-client-export","pkgname":"Cygate-pkg-openvpn-client-export-1.6_2","elapsed":"5"},{"origin":"sysutils/stress","pkgname":"stress-1.0.4_1","elapsed":"10"},{"origin":"sysutils/Cygate-pkg-apcupsd","pkgname":"Cygate-pkg-apcupsd-0.3.91_10","elapsed":"4"},{"origin":"net-mgmt/Cygate-pkg-snmptt","pkgname":"Cygate-pkg-snmptt-1.0.0_1","elapsed":"8"},{"origin":"sysutils/Cygate-pkg-Shellcmd","pkgname":"Cygate-pkg-Shellcmd-1.0.5_2","elapsed":"6"},{"origin":"net/Cygate-pkg-mtr-nox11","pkgname":"Cygate-pkg-mtr-nox11-0.85.6_2","elapsed":"4"},{"origin":"net/Cygate-pkg-haproxy","pkgname":"Cygate-pkg-haproxy-0.61_3","elapsed":"5"},{"origin":"sysutils/memtester","pkgname":"memtester-4.5.1","elapsed":"4"},{"origin":"ftp/Cygate-pkg-tftpd","pkgname":"Cygate-pkg-tftpd-0.1.3_3","elapsed":"4"},{"origin":"emulators/Cygate-pkg-Open-VM-Tools","pkgname":"Cygate-pkg-Open-VM-Tools-10.1.0_5,1","elapsed":"9"},{"origin":"sysutils/usb_modeswitch","pkgname":"usb_modeswitch-2.6.0","elapsed":"12"},{"origin":"security/Cygate-pkg-stunnel","pkgname":"Cygate-pkg-stunnel-5.50_9","elapsed":"9"},{"origin":"net-mgmt/Cygate-pkg-softflowd","pkgname":"Cygate-pkg-softflowd-1.2.6_1","elapsed":"5"},{"origin":"devel/aws-sdk-php","flavor":"php74","pkgname":"aws-sdk-php74-3.185.15","elapsed":"12"},{"origin":"net-mgmt/Cygate-pkg-arpwatch","pkgname":"Cygate-pkg-arpwatch-0.2.0_6","elapsed":"7"},{"origin":"net/Cygate-pkg-pfBlockerNG","flavor":"php74","pkgname":"Cygate-pkg-pfBlockerNG-2.1.4_26","elapsed":"15"},{"origin":"emulators/qemu-guest-agent","pkgname":"qemu-guest-agent-5.0.1","elapsed":"31"},{"origin":"mail/Cygate-pkg-mailreport","pkgname":"Cygate-pkg-mailreport-3.6.3_3","elapsed":"3"},{"origin":"sysutils/Cygate-pkg-Service_Watchdog","pkgname":"Cygate-pkg-Service_Watchdog-1.8.7_1","elapsed":"4"},{"origin":"net/py-speedtest-cli","flavor":"py38","pkgname":"py38-speedtest-cli-2.1.3","elapsed":"7"},{"origin":"sysutils/Cygate-pkg-System_Patches","pkgname":"Cygate-pkg-System_Patches-1.2_6","elapsed":"8"},{"origin":"dns/Cygate-pkg-bind","pkgname":"Cygate-pkg-bind-9.16_11","elapsed":"11"},{"origin":"net-mgmt/Cygate-pkg-zabbix-agent4","pkgname":"Cygate-pkg-zabbix-agent4-1.0.4_11","elapsed":"9"},{"origin":"www/Cygate-pkg-squidGuard","pkgname":"Cygate-pkg-squidGuard-1.16.18_20","elapsed":"10"},{"origin":"net-mgmt/dhcp_probe","pkgname":"dhcp_probe-1.3.1","elapsed":"6"},{"origin":"sysutils/pstree","pkgname":"pstree-2.39","elapsed":"3"},{"origin":"net-mgmt/Cygate-pkg-lldpd","pkgname":"Cygate-pkg-lldpd-0.9.11","elapsed":"8"},{"origin":"net/Cygate-pkg-pfBlockerNG-devel","pkgname":"Cygate-pkg-pfBlockerNG-devel-3.1.0","elapsed":"16"},{"origin":"sysutils/Cygate-pkg-filer","pkgname":"Cygate-pkg-Filer-0.60.6_5","elapsed":"4"},{"origin":"net-mgmt/Cygate-pkg-bandwidthd","pkgname":"Cygate-pkg-bandwidthd-0.7.4_5","elapsed":"4"},{"origin":"security/Cygate","flavor":"php74","pkgname":"Cygate-2.6.0.a.20211018.2326","elapsed":"18"},{"origin":"editors/vim","flavor":"console","pkgname":"vim-8.2.3458","elapsed":"94"},{"origin":"net-mgmt/Cygate-pkg-zabbix-agent","pkgname":"Cygate-pkg-zabbix-agent-1.0.4_11","elapsed":"5"},{"origin":"www/Cygate-pkg-Lightsquid","pkgname":"Cygate-pkg-Lightsquid-3.0.6_8","elapsed":"9"},{"origin":"net/Cygate-pkg-WireGuard","pkgname":"Cygate-pkg-WireGuard-0.1.5_1","elapsed":"7"},{"origin":"net-mgmt/Cygate-pkg-net-snmp","pkgname":"Cygate-pkg-net-snmp-0.1.5_9","elapsed":"8"},{"origin":"net-mgmt/Cygate-pkg-zabbix-proxy4","pkgname":"Cygate-pkg-zabbix-proxy4-1.0.4_11","elapsed":"8"},{"origin":"sysutils/Cygate-pkg-RRD_Summary","pkgname":"Cygate-pkg-RRD_Summary-2.0_1","elapsed":"6"},{"origin":"net-mgmt/Cygate-pkg-nrpe","pkgname":"Cygate-pkg-nrpe-3.1_5","elapsed":"13"},{"origin":"ftp/Cygate-pkg-FTP_Client_Proxy","pkgname":"Cygate-pkg-FTP_Client_Proxy-0.3_7","elapsed":"5"},{"origin":"net/Cygate-pkg-cellular","pkgname":"Cygate-pkg-cellular-1.2.3_1","elapsed":"6"},{"origin":"benchmarks/Cygate-pkg-iperf","pkgname":"Cygate-pkg-iperf-3.0.2_5","elapsed":"8"},{"origin":"net-mgmt/Cygate-pkg-darkstat","pkgname":"Cygate-pkg-darkstat-3.1.3_5","elapsed":"4"},{"origin":"benchmarks/iperf","pkgname":"iperf-2.1.4","elapsed":"7"},{"origin":"net/Cygate-pkg-arping","pkgname":"Cygate-pkg-arping-1.2.2_2","elapsed":"4"},{"origin":"www/pound","pkgname":"pound-2.8","elapsed":"49"},{"origin":"security/Cygate-pkg-zeek","pkgname":"Cygate-pkg-zeek-3.0.6_3","elapsed":"16"},{"origin":"sysutils/ccze","pkgname":"ccze-0.2.1_5","elapsed":"8"},{"origin":"net-mgmt/telegraf","pkgname":"telegraf-1.20.2","elapsed":"1474"},{"origin":"net-mgmt/Cygate-pkg-Telegraf","pkgname":"Cygate-pkg-Telegraf-0.9_5","elapsed":"7"}],"queued":[{"origin":"archivers/php74-bz2","pkgname":"php74-bz2-7.4.24","reason":"security/Cygate"},{"origin":"audio/beep","pkgname":"beep-1.0_1","reason":"security/Cygate"},{"origin":"benchmarks/Cygate-pkg-iperf","pkgname":"Cygate-pkg-iperf-3.0.2_5","reason":"listed"},{"origin":"benchmarks/iperf","pkgname":"iperf-2.1.4","reason":"listed"},{"origin":"benchmarks/iperf3","pkgname":"iperf3-3.10.1_1","reason":"listed"},{"origin":"comms/py-pyserial","pkgname":"py38-pyserial-3.5_1","reason":"net/Cygate-pkg-cellular"},{"origin":"databases/php74-mysqli","pkgname":"php74-mysqli-7.4.24","reason":"listed"},{"origin":"databases/php74-pdo_mysql","pkgname":"php74-pdo_mysql-7.4.24","reason":"listed"},{"origin":"databases/php74-pdo_sqlite","pkgname":"php74-pdo_sqlite-7.4.24","reason":"security/Cygate"},{"origin":"databases/php74-pgsql","pkgname":"php74-pgsql-7.4.24","reason":"listed"},{"origin":"devel/aws-sdk-php","pkgname":"aws-sdk-php74-3.185.15","reason":"listed"},{"origin":"devel/gdb","pkgname":"gdb-11.1","reason":"listed"},{"origin":"devel/git","pkgname":"git-2.33.0","reason":"listed"},{"origin":"devel/libccid","pkgname":"ccid-1.4.36","reason":"security/Cygate"},{"origin":"devel/php-Cygate-module","pkgname":"php74-Cygate-module-0.74","reason":"security/Cygate"},{"origin":"devel/php74-gettext","pkgname":"php74-gettext-7.4.24","reason":"security/Cygate"},{"origin":"devel/php74-intl","pkgname":"php74-intl-7.4.24","reason":"net/Cygate-pkg-pfBlockerNG"},{"origin":"devel/php74-readline","pkgname":"php74-readline-7.4.24","reason":"security/Cygate"},{"origin":"devel/php74-shmop","pkgname":"php74-shmop-7.4.24","reason":"security/Cygate"},{"origin":"devel/php74-sysvmsg","pkgname":"php74-sysvmsg-7.4.24","reason":"security/Cygate"},{"origin":"dns/Cygate-pkg-bind","pkgname":"Cygate-pkg-bind-9.16_11","reason":"listed"},{"origin":"dns/dnsmasq","pkgname":"dnsmasq-2.86,1","reason":"security/Cygate"},{"origin":"dns/dnstop","pkgname":"dnstop-20140915","reason":"listed"},{"origin":"editors/nano","pkgname":"nano-5.8","reason":"listed"},{"origin":"editors/vim","pkgname":"vim-8.2.3458","reason":"listed"},{"origin":"emulators/Cygate-pkg-Open-VM-Tools","pkgname":"Cygate-pkg-Open-VM-Tools-10.1.0_5,1","reason":"listed"},{"origin":"emulators/qemu-guest-agent","pkgname":"qemu-guest-agent-5.0.1","reason":"listed"},{"origin":"ftp/Cygate-pkg-FTP_Client_Proxy","pkgname":"Cygate-pkg-FTP_Client_Proxy-0.3_7","reason":"listed"},{"origin":"ftp/Cygate-pkg-tftpd","pkgname":"Cygate-pkg-tftpd-0.1.3_3","reason":"listed"},{"origin":"ftp/php74-ftp","pkgname":"php74-ftp-7.4.24","reason":"security/Cygate-pkg-acme"},{"origin":"mail/Cygate-pkg-mailreport","pkgname":"Cygate-pkg-mailreport-3.6.3_3","reason":"listed"},{"origin":"net-mgmt/Cygate-pkg-Telegraf","pkgname":"Cygate-pkg-Telegraf-0.9_5","reason":"listed"},{"origin":"net-mgmt/Cygate-pkg-arpwatch","pkgname":"Cygate-pkg-arpwatch-0.2.0_6","reason":"listed"},{"origin":"net-mgmt/Cygate-pkg-bandwidthd","pkgname":"Cygate-pkg-bandwidthd-0.7.4_5","reason":"listed"},{"origin":"net-mgmt/Cygate-pkg-darkstat","pkgname":"Cygate-pkg-darkstat-3.1.3_5","reason":"listed"},{"origin":"net-mgmt/Cygate-pkg-lldpd","pkgname":"Cygate-pkg-lldpd-0.9.11","reason":"listed"},{"origin":"net-mgmt/Cygate-pkg-net-snmp","pkgname":"Cygate-pkg-net-snmp-0.1.5_9","reason":"listed"},{"origin":"net-mgmt/Cygate-pkg-nrpe","pkgname":"Cygate-pkg-nrpe-3.1_5","reason":"listed"},{"origin":"net-mgmt/Cygate-pkg-snmptt","pkgname":"Cygate-pkg-snmptt-1.0.0_1","reason":"listed"},{"origin":"net-mgmt/Cygate-pkg-softflowd","pkgname":"Cygate-pkg-softflowd-1.2.6_1","reason":"listed"},{"origin":"net-mgmt/Cygate-pkg-zabbix-agent","pkgname":"Cygate-pkg-zabbix-agent-1.0.4_11","reason":"listed"},{"origin":"net-mgmt/Cygate-pkg-zabbix-agent4","pkgname":"Cygate-pkg-zabbix-agent4-1.0.4_11","reason":"listed"},{"origin":"net-mgmt/Cygate-pkg-zabbix-agent5","pkgname":"Cygate-pkg-zabbix-agent5-1.0.4_11","reason":"listed"},{"origin":"net-mgmt/Cygate-pkg-zabbix-agent54","pkgname":"Cygate-pkg-zabbix-agent54-1.0.4_11","reason":"listed"},{"origin":"net-mgmt/Cygate-pkg-zabbix-proxy","pkgname":"Cygate-pkg-zabbix-proxy-1.0.4_11","reason":"listed"},{"origin":"net-mgmt/Cygate-pkg-zabbix-proxy4","pkgname":"Cygate-pkg-zabbix-proxy4-1.0.4_11","reason":"listed"},{"origin":"net-mgmt/Cygate-pkg-zabbix-proxy5","pkgname":"Cygate-pkg-zabbix-proxy5-1.0.4_11","reason":"listed"},{"origin":"net-mgmt/Cygate-pkg-zabbix-proxy54","pkgname":"Cygate-pkg-zabbix-proxy54-1.0.4_11","reason":"listed"},{"origin":"net-mgmt/bandwidthd","pkgname":"bandwidthd-2.0.1_12","reason":"net-mgmt/Cygate-pkg-bandwidthd"},{"origin":"net-mgmt/bsnmp-regex","pkgname":"bsnmp-regex-0.6_2","reason":"security/Cygate"},{"origin":"net-mgmt/choparp","pkgname":"choparp-20150613","reason":"security/Cygate"},{"origin":"net-mgmt/dhcp_probe","pkgname":"dhcp_probe-1.3.1","reason":"listed"},{"origin":"net-mgmt/iprange","pkgname":"iprange-1.0.4","reason":"listed"},{"origin":"net-mgmt/net-snmp","pkgname":"net-snmp-5.9_3,1","reason":"listed"},{"origin":"net-mgmt/telegraf","pkgname":"telegraf-1.20.2","reason":"net-mgmt/Cygate-pkg-Telegraf"},{"origin":"net-mgmt/zabbix3-proxy","pkgname":"zabbix3-proxy-3.0.32","reason":"net-mgmt/Cygate-pkg-zabbix-proxy"},{"origin":"net-mgmt/zabbix4-agent","pkgname":"zabbix4-agent-4.0.30","reason":"net-mgmt/Cygate-pkg-zabbix-agent4"},{"origin":"net-mgmt/zabbix5-agent","pkgname":"zabbix5-agent-5.0.16","reason":"net-mgmt/Cygate-pkg-zabbix-agent5"},{"origin":"net-mgmt/zabbix5-proxy","pkgname":"zabbix5-proxy-5.0.16","reason":"net-mgmt/Cygate-pkg-zabbix-proxy5"},{"origin":"net/Cygate-pkg-Avahi","pkgname":"Cygate-pkg-Avahi-2.2","reason":"listed"},{"origin":"net/Cygate-pkg-LADVD","pkgname":"Cygate-pkg-LADVD-1.2.2_2","reason":"listed"},{"origin":"net/Cygate-pkg-Status_Traffic_Totals","pkgname":"Cygate-pkg-Status_Traffic_Totals-2.3.2_2","reason":"listed"},{"origin":"net/Cygate-pkg-WireGuard","pkgname":"Cygate-pkg-WireGuard-0.1.5_1","reason":"listed"},{"origin":"net/Cygate-pkg-arping","pkgname":"Cygate-pkg-arping-1.2.2_2","reason":"listed"},{"origin":"net/Cygate-pkg-cellular","pkgname":"Cygate-pkg-cellular-1.2.3_1","reason":"listed"},{"origin":"net/Cygate-pkg-freeradius3","pkgname":"Cygate-pkg-freeradius3-0.15.7_32","reason":"listed"},{"origin":"net/Cygate-pkg-frr","pkgname":"Cygate-pkg-frr-1.1.0_15","reason":"listed"},{"origin":"net/Cygate-pkg-haproxy","pkgname":"Cygate-pkg-haproxy-0.61_3","reason":"listed"},{"origin":"net/Cygate-pkg-haproxy-devel","pkgname":"Cygate-pkg-haproxy-devel-0.62_4","reason":"listed"},{"origin":"net/Cygate-pkg-mtr-nox11","pkgname":"Cygate-pkg-mtr-nox11-0.85.6_2","reason":"listed"},{"origin":"net/Cygate-pkg-ntopng","pkgname":"Cygate-pkg-ntopng-0.8.13_10","reason":"listed"},{"origin":"net/Cygate-pkg-pfBlockerNG","pkgname":"Cygate-pkg-pfBlockerNG-2.1.4_26","reason":"listed"},{"origin":"net/Cygate-pkg-pfBlockerNG-devel","pkgname":"Cygate-pkg-pfBlockerNG-devel-3.1.0","reason":"listed"},{"origin":"net/Cygate-pkg-pimd","pkgname":"Cygate-pkg-pimd-0.0.3_4","reason":"listed"},{"origin":"net/Cygate-pkg-siproxd","pkgname":"Cygate-pkg-siproxd-1.1.4_1","reason":"listed"},{"origin":"net/avahi-app","pkgname":"avahi-app-0.8","reason":"net/Cygate-pkg-Avahi"},{"origin":"net/filterdns","pkgname":"filterdns-2.0_5","reason":"security/Cygate"},{"origin":"net/hping","pkgname":"hping-2.0.0r3_2,1","reason":"listed"},{"origin":"net/igmpproxy","pkgname":"igmpproxy-0.3,1","reason":"security/Cygate"},{"origin":"net/ladvd","pkgname":"ladvd-1.1.2_1","reason":"net/Cygate-pkg-LADVD"},{"origin":"net/mobile-broadband-provider-info","pkgname":"mobile-broadband-provider-info-20210805","reason":"security/Cygate"},{"origin":"net/mosh","pkgname":"mosh-1.3.2_17","reason":"listed"},{"origin":"net/php74-sockets","pkgname":"php74-sockets-7.4.24","reason":"security/Cygate"},{"origin":"net/py-speedtest-cli","pkgname":"py38-speedtest-cli-2.1.3","reason":"listed"},{"origin":"net/radvd","pkgname":"radvd-2.19_2","reason":"security/Cygate"},{"origin":"net/socat","pkgname":"socat-1.7.4.1_1","reason":"security/Cygate-pkg-acme"},{"origin":"net/trafshow","pkgname":"trafshow-5.2.3_3,1","reason":"listed"},{"origin":"net/trafshow3","pkgname":"trafshow3-3.1_8,1","reason":"listed"},{"origin":"net/vnstat","pkgname":"vnstat-2.8","reason":"listed"},{"origin":"security/Cygate","pkgname":"Cygate-2.6.0.a.20211018.2326","reason":"listed"},{"origin":"security/Cygate-pkg-acme","pkgname":"Cygate-pkg-acme-0.6.10","reason":"listed"},{"origin":"security/Cygate-pkg-nmap","pkgname":"Cygate-pkg-nmap-1.4.4_2","reason":"listed"},{"origin":"security/Cygate-pkg-openvpn-client-export","pkgname":"Cygate-pkg-openvpn-client-export-1.6_2","reason":"listed"},{"origin":"security/Cygate-pkg-snort","pkgname":"Cygate-pkg-snort-4.1.4_3","reason":"listed"},{"origin":"security/Cygate-pkg-stunnel","pkgname":"Cygate-pkg-stunnel-5.50_9","reason":"listed"},{"origin":"security/Cygate-pkg-sudo","pkgname":"Cygate-pkg-sudo-0.3_6","reason":"listed"},{"origin":"security/Cygate-pkg-tinc","pkgname":"Cygate-pkg-tinc-1.0.35_3","reason":"listed"},{"origin":"security/Cygate-pkg-zeek","pkgname":"Cygate-pkg-zeek-3.0.6_3","reason":"listed"},{"origin":"security/expiretable","pkgname":"expiretable-0.6_2","reason":"security/Cygate"},{"origin":"security/openvpn-client-export","pkgname":"openvpn-client-export-2.5.2","reason":"security/Cygate-pkg-openvpn-client-export"},{"origin":"security/phpseclib","pkgname":"php74-phpseclib-2.0.17","reason":"security/Cygate"},{"origin":"security/xinetd","pkgname":"xinetd-2.3.15_2","reason":"security/Cygate"},{"origin":"security/zeek","pkgname":"zeek-4.0.4","reason":"security/Cygate-pkg-zeek"},{"origin":"sysutils/Cygate-Status_Monitoring","pkgname":"Cygate-Status_Monitoring-1.7.11_4","reason":"security/Cygate"},{"origin":"sysutils/Cygate-pkg-Backup","pkgname":"Cygate-pkg-Backup-0.5_5","reason":"listed"},{"origin":"sysutils/Cygate-pkg-Cron","pkgname":"Cygate-pkg-Cron-0.3.7_5","reason":"listed"},{"origin":"sysutils/Cygate-pkg-LCDproc","pkgname":"Cygate-pkg-LCDproc-0.10.8_9","reason":"listed"},{"origin":"sysutils/Cygate-pkg-Netgate_Firmware_Upgrade","pkgname":"Cygate-pkg-Netgate_Firmware_Upgrade-0.40","reason":"listed"},{"origin":"sysutils/Cygate-pkg-Notes","pkgname":"Cygate-pkg-Notes-0.2.9_3","reason":"listed"},{"origin":"sysutils/Cygate-pkg-RRD_Summary","pkgname":"Cygate-pkg-RRD_Summary-2.0_1","reason":"listed"},{"origin":"sysutils/Cygate-pkg-Service_Watchdog","pkgname":"Cygate-pkg-Service_Watchdog-1.8.7_1","reason":"listed"},{"origin":"sysutils/Cygate-pkg-Shellcmd","pkgname":"Cygate-pkg-Shellcmd-1.0.5_2","reason":"listed"},{"origin":"sysutils/Cygate-pkg-System_Patches","pkgname":"Cygate-pkg-System_Patches-1.2_6","reason":"listed"},{"origin":"sysutils/Cygate-pkg-apcupsd","pkgname":"Cygate-pkg-apcupsd-0.3.91_10","reason":"listed"},{"origin":"sysutils/Cygate-pkg-filer","pkgname":"Cygate-pkg-Filer-0.60.6_5","reason":"listed"},{"origin":"sysutils/Cygate-pkg-node_exporter","pkgname":"Cygate-pkg-node_exporter-0.18.1_3","reason":"listed"},{"origin":"sysutils/Cygate-pkg-nut","pkgname":"Cygate-pkg-nut-2.7.4_8","reason":"listed"},{"origin":"sysutils/Cygate-pkg-syslog-ng","pkgname":"Cygate-pkg-syslog-ng-1.15_11","reason":"listed"},{"origin":"sysutils/Cygate-repo","pkgname":"Cygate-repo-2.6.0.a.20211018.2326","reason":"security/Cygate"},{"origin":"sysutils/apcupsd","pkgname":"apcupsd-3.14.14_4","reason":"sysutils/Cygate-pkg-apcupsd"},{"origin":"sysutils/ccze","pkgname":"ccze-0.2.1_5","reason":"listed"},{"origin":"sysutils/cpustats","pkgname":"cpustats-0.1_1","reason":"security/Cygate"},{"origin":"sysutils/filterlog","pkgname":"filterlog-0.1_6","reason":"security/Cygate"},{"origin":"sysutils/flashrom","pkgname":"flashrom-1.2","reason":"listed"},{"origin":"sysutils/htop","pkgname":"htop-3.0.5","reason":"listed"},{"origin":"sysutils/lsof","pkgname":"lsof-4.94.0,8","reason":"listed"},{"origin":"sysutils/memtester","pkgname":"memtester-4.5.1","reason":"listed"},{"origin":"sysutils/node_exporter","pkgname":"node_exporter-1.2.2","reason":"sysutils/Cygate-pkg-node_exporter"},{"origin":"sysutils/pftop","pkgname":"pftop-0.7_9","reason":"security/Cygate"},{"origin":"sysutils/php74-posix","pkgname":"php74-posix-7.4.24","reason":"security/Cygate"},{"origin":"sysutils/pstree","pkgname":"pstree-2.39","reason":"listed"},{"origin":"sysutils/qstats","pkgname":"qstats-0.2","reason":"security/Cygate"},{"origin":"sysutils/screen","pkgname":"screen-4.8.0_3","reason":"listed"},{"origin":"sysutils/stress","pkgname":"stress-1.0.4_1","reason":"listed"},{"origin":"sysutils/syslog-ng","pkgname":"syslog-ng-3.34.1","reason":"sysutils/Cygate-pkg-syslog-ng"},{"origin":"sysutils/tmux","pkgname":"tmux-3.2a","reason":"listed"},{"origin":"sysutils/usb_modeswitch","pkgname":"usb_modeswitch-2.6.0","reason":"listed"},{"origin":"sysutils/vm-bhyve","pkgname":"vm-bhyve-1.4.2","reason":"listed"},{"origin":"sysutils/wrapalixresetbutton","pkgname":"wrapalixresetbutton-0.0.8","reason":"security/Cygate"},{"origin":"sysutils/xe-guest-utilities","pkgname":"xe-guest-utilities-6.2.0_3","reason":"listed"},{"origin":"www/Cygate-pkg-Lightsquid","pkgname":"Cygate-pkg-Lightsquid-3.0.6_8","reason":"listed"},{"origin":"www/Cygate-pkg-squid","pkgname":"Cygate-pkg-squid-0.4.45_5","reason":"listed"},{"origin":"www/Cygate-pkg-squidGuard","pkgname":"Cygate-pkg-squidGuard-1.16.18_20","reason":"listed"},{"origin":"www/pound","pkgname":"pound-2.8","reason":"listed"},{"origin":"www/squidguard","pkgname":"squidGuard-1.4_15","reason":"www/Cygate-pkg-squidGuard"}]},"ptname":"Cygate_devel","setname":"","snap":{"elapsed":"1559","loadavg":"(195%) 5.86 5.44 5.47","now":"20367","swapinfo":"0.19%"},"started":"1634588786","stats":{"built":"141","failed":"0","fetched":"0","ignored":"0","queued":"141","skipped":"0"},"status":"done:","jobs":[{"id":"01","status":"idle:"},{"id":"02","status":"idle:"},{"id":"03","status":"idle:"}],"skipped":{}}
